ibus_theme_tools/__init__.py
ibus_theme_tools/ibus_theme_tools.py
ibus_theme_tools/merge-gresource.sh
ibus_theme_tools/locale/fr/LC_MESSAGES/IBus-Theme.mo
ibus_theme_tools/locale/zh_CN/LC_MESSAGES/IBus-Theme.mo
ibus_theme_tools/locale/zh_HK/LC_MESSAGES/IBus-Theme.mo
ibus_theme_tools/locale/zh_TW/LC_MESSAGES/IBus-Theme.mo
ibus_theme_tools-4.2.0.dist-info/LICENSE
ibus_theme_tools-4.2.0.dist-info/METADATA
ibus_theme_tools-4.2.0.dist-info/WHEEL
ibus_theme_tools-4.2.0.dist-info/entry_points.txt
ibus_theme_tools-4.2.0.dist-info/top_level.txt
ibus_theme_tools-4.2.0.dist-info/RECORD
