Metadata-Version: 2.1
Name: ibus-theme-tools
Version: 4.2.0
Summary: Generate the IBus GTK or GNOME Shell theme from existing themes.
Home-page: https://github.com/openSUSE/IBus-Theme-Tools
Author: Hollow Man (Domain Address)
Author-email: hollowman@hollowman.ml
License: GPL-3.0-or-later
Project-URL: Bug Tracker, https://github.com/openSUSE/IBus-Theme-Tools/issues
Platform: UNKNOWN
Classifier: Programming Language :: Python :: 3
Classifier: License :: OSI Approved :: GNU General Public License v3 or later (GPLv3+)
Classifier: Operating System :: Unix
Classifier: Topic :: Desktop Environment :: Gnome
Classifier: Natural Language :: Chinese (Simplified)
Classifier: Natural Language :: English
License-File: LICENSE
Requires-Dist: tinycss2
